redismap.py
redismap-0.1.0.dist-info/LICENSE.md
redismap-0.1.0.dist-info/WHEEL
redismap-0.1.0.dist-info/METADATA
redismap-0.1.0.dist-info/RECORD
